pelican_bootstrap_figures/__init__.py
pelican_bootstrap_figures/pelican_bootstrap_figures.py
pelican_bootstrap_figures-1.0.1.dist-info/LICENSE
pelican_bootstrap_figures-1.0.1.dist-info/METADATA
pelican_bootstrap_figures-1.0.1.dist-info/WHEEL
pelican_bootstrap_figures-1.0.1.dist-info/top_level.txt
pelican_bootstrap_figures-1.0.1.dist-info/RECORD
