Metadata-Version: 2.1
Name: pelican-bootstrap-figures
Version: 1.0.1
Summary: Bootstrap figures for Pelican
Home-page: https://github.com/rcoenmans/pelican-bootstrap-figures
Author: Robbie Coenmans
Author-email: robbie.coenmans@outlook.com
License: MIT License
Platform: UNKNOWN
Classifier: Development Status :: 5 - Production/Stable
Classifier: Intended Audience :: Developers
Classifier: Programming Language :: Python :: 3
Classifier: Programming Language :: Python :: 3.0
Classifier: Programming Language :: Python :: 3.1
Classifier: Programming Language :: Python :: 3.2
Classifier: Programming Language :: Python :: 3.3
Classifier: Programming Language :: Python :: 3.4
Classifier: Programming Language :: Python :: 3.5
Classifier: Programming Language :: Python :: 3.6
Classifier: Programming Language :: Python :: 3.7
Classifier: Programming Language :: Python :: 3 :: Only
Classifier: License :: OSI Approved :: MIT License
Requires-Dist: BeautifulSoup4
